{
    "id": "BS-SL",
    "name": "BS-SL",
    "title": "Barren Sands And Shattered Lands",
    "description": "A system for playing Barren Sands And Shattered Lands games",
    "authors": [{
        "name": "Jazpixel",
        "discord": "Jazpixel"
    }],
    "version": "1.0.0",
    "minimumCoreVersion": 11,
    "compatibility" : {
        "minimum" : 11,
        "verified" : 11,
        "maximum" : 12
    },
    "esmodules": [
        "bssl.js"
    ],
    "styles": [
        "bssl.css"
    ],
    "packs": [

    ],
    "languages": [

    ],
    "gridDistance": 1,
    "gridUnits": "m",
    "primaryTokenAttribute": "hp",
    "initiative": "initiative"
}